shell_sage/__init__.py
shell_sage/_modidx.py
shell_sage/config.py
shell_sage/core.py
shell_sage-1.0.4.dist-info/licenses/LICENSE
shell_sage-1.0.4.dist-info/METADATA
shell_sage-1.0.4.dist-info/WHEEL
shell_sage-1.0.4.dist-info/entry_points.txt
shell_sage-1.0.4.dist-info/top_level.txt
shell_sage-1.0.4.dist-info/RECORD
