Metadata-Version: 2.4
Name: shell-sage
Version: 1.0.4
Summary: Your favorite AI buddy right in your terminal
Home-page: https://github.com/AnswerDotAI/shell_sage
Author: ncoop57
Author-email: nc@answer.ai
License: Apache Software License 2.0
Keywords: nbdev jupyter notebook python
Classifier: Development Status :: 4 - Beta
Classifier: Intended Audience :: Developers
Classifier: Natural Language :: English
Classifier: Programming Language :: Python :: 3.10
Classifier: Programming Language :: Python :: 3.11
Classifier: Programming Language :: Python :: 3.12
Classifier: License :: OSI Approved :: Apache Software License
Requires-Python: >=3.10
License-File: LICENSE
Requires-Dist: fastcore>=1.7.29
Requires-Dist: fastlite
Requires-Dist: lisette>=0.0.6
Requires-Dist: msglm
Requires-Dist: pyperclip
Requires-Dist: rich
Requires-Dist: safecmd
Provides-Extra: dev
Dynamic: author
Dynamic: author-email
Dynamic: classifier
Dynamic: description
Dynamic: description-content-type
Dynamic: home-page
Dynamic: keywords
Dynamic: license
Dynamic: license-file
Dynamic: provides-extra
Dynamic: requires-dist
Dynamic: requires-python
Dynamic: summary
